{"files":{"apps/worker/dist/services/vk/vk-relevance.service.js":{"size":3132,"mtime_nanos":1776605660325858095,"mode":420,"is_dir":false},"apps/worker/dist/adapters/source-adapter.interface.js":{"size":77,"mtime_nanos":1776605660272857032,"mode":420,"is_dir":false},"apps/worker/dist/common":{"size":0,"mtime_nanos":0,"mode":0,"is_dir":true},"apps/worker/dist/processors/source-discovery.processor.js":{"size":3506,"mtime_nanos":1776605660284857273,"mode":420,"is_dir":false},"apps/worker/dist/processors/vk":{"size":0,"mtime_nanos":0,"mode":0,"is_dir":true},"apps/worker/dist/processors":{"size":0,"mtime_nanos":0,"mode":0,"is_dir":true},"apps/worker/dist/services/rating.service.js":{"size":1894,"mtime_nanos":1776605660224856070,"mode":420,"is_dir":false},"apps/worker/dist/scripts/inspect-sync-queues.js":{"size":1532,"mtime_nanos":1776605660336858315,"mode":420,"is_dir":false},"apps/worker/dist/processors/vk/vk-post-search.processor.js":{"size":3280,"mtime_nanos":1776605660331858215,"mode":420,"is_dir":false},"apps/worker/dist/common/prisma":{"size":0,"mtime_nanos":0,"mode":0,"is_dir":true},"apps/worker/dist/common/logging":{"size":0,"mtime_nanos":0,"mode":0,"is_dir":true},"apps/worker/dist/adapters/yandex.adapter.js":{"size":1635,"mtime_nanos":1776605660279857173,"mode":420,"is_dir":false},"apps/worker/dist/adapters/vk.adapter.js":{"size":6795,"mtime_nanos":1776605660231856211,"mode":420,"is_dir":false},"apps/worker/dist/services":{"size":0,"mtime_nanos":0,"mode":0,"is_dir":true},"apps/worker/dist/adapters":{"size":0,"mtime_nanos":0,"mode":0,"is_dir":true},"apps/worker/dist/common/logging/logger.js":{"size":373,"mtime_nanos":1776605660281857213,"mode":420,"is_dir":false},"apps/worker/dist/services/vk/vk-playwright-search.service.js":{"size":35786,"mtime_nanos":1776605660323858055,"mode":420,"is_dir":false},"apps/worker/dist/adapters/source-adapter.factory.js":{"size":1071,"mtime_nanos":1776605660280857193,"mode":420,"is_dir":false},"apps/worker/dist/processors/notifications.processor.js":{"size":2130,"mtime_nanos":1776605660296857514,"mode":420,"is_dir":false},"apps/worker/dist/common/utils":{"size":0,"mtime_nanos":0,"mode":0,"is_dir":true},"apps/worker/dist/adapters/webmention.adapter.js":{"size":1268,"mtime_nanos":1776605660276857113,"mode":420,"is_dir":false},"apps/worker/dist/adapters/mock.adapter.js":{"size":917,"mtime_nanos":1776605660273857052,"mode":420,"is_dir":false},"apps/worker/.turbo/turbo-build.log":{"size":83,"mtime_nanos":1776605660391859418,"mode":420,"is_dir":false},"apps/worker/dist/services/relevance.service.js":{"size":1799,"mtime_nanos":1776605660339858375,"mode":420,"is_dir":false},"apps/worker/dist/processors/reviews-sync.processor.js":{"size":4562,"mtime_nanos":1776605660287857333,"mode":420,"is_dir":false},"apps/worker/dist/scheduler":{"size":0,"mtime_nanos":0,"mode":0,"is_dir":true},"apps/worker/dist/services/vk/vk.service.js":{"size":14210,"mtime_nanos":1776605660241856411,"mode":420,"is_dir":false},"apps/worker/dist/processors/vk/vk-brand-match.processor.js":{"size":2127,"mtime_nanos":1776605660305857694,"mode":420,"is_dir":false},"apps/worker/dist/common/prisma/prisma.service.js":{"size":1050,"mtime_nanos":1776605660193855449,"mode":420,"is_dir":false},"apps/worker/dist/app.module.js":{"size":4927,"mtime_nanos":1776605660333858255,"mode":420,"is_dir":false},"apps/worker/dist/processors/vk/vk-reconcile.processor.js":{"size":2115,"mtime_nanos":1776605660306857714,"mode":420,"is_dir":false},"apps/worker/dist/adapters/twogis.adapter.js":{"size":1534,"mtime_nanos":1776605660277857133,"mode":420,"is_dir":false},"apps/worker/dist/processors/vk/vk-owned-community.processor.js":{"size":2832,"mtime_nanos":1776605660302857634,"mode":420,"is_dir":false},"apps/worker/dist/scheduler/scheduler.service.js":{"size":4803,"mtime_nanos":1776605660212855830,"mode":420,"is_dir":false},"apps/worker/dist/processors/mentions-sync.processor.js":{"size":3848,"mtime_nanos":1776605660290857393,"mode":420,"is_dir":false},"apps/worker/dist/queues":{"size":0,"mtime_nanos":0,"mode":0,"is_dir":true},"apps/worker/dist/processors/vk/vk-comments.processor.js":{"size":2300,"mtime_nanos":1776605660303857654,"mode":420,"is_dir":false},"apps/worker/dist/services/dedup.service.js":{"size":4239,"mtime_nanos":1776605660220855990,"mode":420,"is_dir":false},"apps/worker/dist/processors/vk/vk-priority-communities.processor.js":{"size":2905,"mtime_nanos":1776605660300857594,"mode":420,"is_dir":false},"apps/worker/dist/common/utils/hash.util.js":{"size":419,"mtime_nanos":1776605660214855870,"mode":420,"is_dir":false},"apps/worker/dist/common/utils/sentiment.util.js":{"size":650,"mtime_nanos":1776605660216855910,"mode":420,"is_dir":false},"apps/worker/dist/services/vk/vk-comments.service.js":{"size":3338,"mtime_nanos":1776605660272857032,"mode":420,"is_dir":false},"apps/worker/dist/queues/job.names.js":{"size":630,"mtime_nanos":1776605660203855649,"mode":420,"is_dir":false},"apps/worker/dist/services/sentiment.service.js":{"size":1221,"mtime_nanos":1776605660340858396,"mode":420,"is_dir":false},"apps/worker/dist/common/prisma/prisma.module.js":{"size":1092,"mtime_nanos":1776605660195855489,"mode":420,"is_dir":false},"apps/worker/dist/services/vk/vk-community-sync.service.js":{"size":18212,"mtime_nanos":1776605660266856912,"mode":420,"is_dir":false},"apps/worker/dist/common/utils/normalize.util.js":{"size":245,"mtime_nanos":1776605660215855890,"mode":420,"is_dir":false},"apps/worker/dist/main.js":{"size":494,"mtime_nanos":1776605660334858275,"mode":420,"is_dir":false},"apps/worker/dist/common/utils/relevance.util.js":{"size":1098,"mtime_nanos":1776605660335858295,"mode":420,"is_dir":false},"apps/worker/dist/processors/reconcile.processor.js":{"size":2411,"mtime_nanos":1776605660294857473,"mode":420,"is_dir":false},"apps/worker/dist/services/vk/vk-community.service.js":{"size":4217,"mtime_nanos":1776605660269856972,"mode":420,"is_dir":false},"apps/worker/dist/services/vk/vk-auth-session.service.js":{"size":3499,"mtime_nanos":1776605660308857754,"mode":420,"is_dir":false},"apps/worker/dist/queues/queue.names.js":{"size":671,"mtime_nanos":1776605660197855529,"mode":420,"is_dir":false},"apps/worker/dist/queues/bullmq.module.js":{"size":2116,"mtime_nanos":1776605660201855609,"mode":420,"is_dir":false},"apps/worker/dist/services/mention.service.js":{"size":1422,"mtime_nanos":1776605660222856030,"mode":420,"is_dir":false},"apps/worker/dist/processors/vk/vk-brand-search.processor.js":{"size":3182,"mtime_nanos":1776605660298857554,"mode":420,"is_dir":false},"apps/worker/dist/services/vk/vk-brand-search.service.js":{"size":11930,"mtime_nanos":1776605660249856571,"mode":420,"is_dir":false},"apps/worker/dist/adapters/google.adapter.js":{"size":1534,"mtime_nanos":1776605660274857073,"mode":420,"is_dir":false},"apps/worker/dist/services/vk/vk-post-search.service.js":{"size":12573,"mtime_nanos":1776605660330858195,"mode":420,"is_dir":false},"apps/worker/dist/processors/rating-refresh.processor.js":{"size":3583,"mtime_nanos":1776605660292857433,"mode":420,"is_dir":false},"apps/worker/dist":{"size":0,"mtime_nanos":0,"mode":0,"is_dir":true},"apps/worker/dist/services/vk":{"size":0,"mtime_nanos":0,"mode":0,"is_dir":true},"apps/worker/dist/scripts":{"size":0,"mtime_nanos":0,"mode":0,"is_dir":true}},"order":["apps/worker/.turbo/turbo-build.log","apps/worker/dist","apps/worker/dist/adapters","apps/worker/dist/adapters/google.adapter.js","apps/worker/dist/adapters/mock.adapter.js","apps/worker/dist/adapters/source-adapter.factory.js","apps/worker/dist/adapters/source-adapter.interface.js","apps/worker/dist/adapters/twogis.adapter.js","apps/worker/dist/adapters/vk.adapter.js","apps/worker/dist/adapters/webmention.adapter.js","apps/worker/dist/adapters/yandex.adapter.js","apps/worker/dist/app.module.js","apps/worker/dist/common","apps/worker/dist/common/logging","apps/worker/dist/common/logging/logger.js","apps/worker/dist/common/prisma","apps/worker/dist/common/prisma/prisma.module.js","apps/worker/dist/common/prisma/prisma.service.js","apps/worker/dist/common/utils","apps/worker/dist/common/utils/hash.util.js","apps/worker/dist/common/utils/normalize.util.js","apps/worker/dist/common/utils/relevance.util.js","apps/worker/dist/common/utils/sentiment.util.js","apps/worker/dist/main.js","apps/worker/dist/processors","apps/worker/dist/processors/mentions-sync.processor.js","apps/worker/dist/processors/notifications.processor.js","apps/worker/dist/processors/rating-refresh.processor.js","apps/worker/dist/processors/reconcile.processor.js","apps/worker/dist/processors/reviews-sync.processor.js","apps/worker/dist/processors/source-discovery.processor.js","apps/worker/dist/processors/vk","apps/worker/dist/processors/vk/vk-brand-match.processor.js","apps/worker/dist/processors/vk/vk-brand-search.processor.js","apps/worker/dist/processors/vk/vk-comments.processor.js","apps/worker/dist/processors/vk/vk-owned-community.processor.js","apps/worker/dist/processors/vk/vk-post-search.processor.js","apps/worker/dist/processors/vk/vk-priority-communities.processor.js","apps/worker/dist/processors/vk/vk-reconcile.processor.js","apps/worker/dist/queues","apps/worker/dist/queues/bullmq.module.js","apps/worker/dist/queues/job.names.js","apps/worker/dist/queues/queue.names.js","apps/worker/dist/scheduler","apps/worker/dist/scheduler/scheduler.service.js","apps/worker/dist/scripts","apps/worker/dist/scripts/inspect-sync-queues.js","apps/worker/dist/services","apps/worker/dist/services/dedup.service.js","apps/worker/dist/services/mention.service.js","apps/worker/dist/services/rating.service.js","apps/worker/dist/services/relevance.service.js","apps/worker/dist/services/sentiment.service.js","apps/worker/dist/services/vk","apps/worker/dist/services/vk/vk-auth-session.service.js","apps/worker/dist/services/vk/vk-brand-search.service.js","apps/worker/dist/services/vk/vk-comments.service.js","apps/worker/dist/services/vk/vk-community-sync.service.js","apps/worker/dist/services/vk/vk-community.service.js","apps/worker/dist/services/vk/vk-playwright-search.service.js","apps/worker/dist/services/vk/vk-post-search.service.js","apps/worker/dist/services/vk/vk-relevance.service.js","apps/worker/dist/services/vk/vk.service.js"]}